CHANGELOG.rst
LICENSE.txt
MANIFEST.in
README.rst
setup.py
scorr/__init__.py
scorr/_cov_matrices_nofft.py
scorr/corr2.py
scorr/corr3.py
scorr/helpers.py
scorr.egg-info/PKG-INFO
scorr.egg-info/SOURCES.txt
scorr.egg-info/dependency_links.txt
scorr.egg-info/not-zip-safe
scorr.egg-info/requires.txt
scorr.egg-info/top_level.txt
tests/__init__.py
tests/test_corr2.py
tests/test_corr3.py
tests/test_helpers.py